cy_account/__init__.py
cy_account/test.py
cy_account-0.1.16.dist-info/METADATA
cy_account-0.1.16.dist-info/WHEEL
cy_account-0.1.16.dist-info/top_level.txt
cy_account-0.1.16.dist-info/RECORD
