Metadata-Version: 2.1
Name: cy-account
Version: 0.1.16
Summary: edited by myself
Author: luyuan
Author-email: 136735431@qq.com
Classifier: Programming Language :: Python :: 3
Classifier: License :: OSI Approved :: MIT License
Classifier: Operating System :: OS Independent
Requires-Python: >=3
Requires-Dist: pydantic
Requires-Dist: fastapi
Requires-Dist: redis
